{
  "$schema": "https://schema.management.azure.com/schemas/2019-04-01/deploymentParameters.json#",
  "contentVersion": "1.0.0.0",
  "parameters": {
    "workspaceName": {
      "value": "databricks-cpp-data-prd-we-01"
    },
    "customVirtualNetworkId": {
      "value": "/subscriptions/8964f3c1-44f5-4094-80eb-4334845bdfb1/resourceGroups/rg-cpp-pltf-net-prd-we-01/providers/Microsoft.Network/virtualNetworks/vnet-cpp-pltf-prd-we-01"
    },
    "customPublicSubnetName": {
      "value": "snet-cpp-data-dbrpub-prd-we-01"
    },
    "customPrivateSubnetName": {
      "value": "snet-cpp-data-dbrpri-prd-we-01"
    },
    "tags": {
      "value": {
        "Environment": "Production"
      }
    }
  }
}