{
    "$schema": "https://schema.management.azure.com/schemas/2019-04-01/deploymentParameters.json#",
    "contentVersion": "1.0.0.0",
    "parameters": {
        "apiManagementServiceName": {
            "value": "apim-cpd-shrd-uat-we-01"
        },
        "apiName": {
            "value": "EventIntegrationApi"
        },
        "apiDisplayName": {
            "value": "Event Integration API"
        },
        "apiDescription": {
            "value": "Event Integration API for UAT"
        },
        "apiPath": {
            "value": "eventintegration"
        },
        "apiPolicyLogicAppName": {
            "value": "logic-cpd-apps-route-uat-we-01"
        },
        "apiPolicyLogicAppRG": {
            "value": "rg-cpd-apps-int-uat-we-01"
        },
        "openIdConfigUrl": {
            "value": "https://login.microsoftonline.com/24f9d756-bf0c-43e9-ad5e-2073ae2d6698/v2.0/.well-known/openid-configuration"
          },
          "audienceId": {
            "value": "bc67474e-612b-4d7f-b75a-ac54d45f143a"
          },
          "issuerUrl":{
            "value": "https://tasmucpb2cnonprod.b2clogin.com/24f9d756-bf0c-43e9-ad5e-2073ae2d6698/v2.0/"
          },
        "apiOperations": {
            "value": [
                {
                    "operationName": "messages",
                    "displayName": "Messages",
                    "urlTemplate": "/messages",
                    "method": "POST",
                    "description": "Send messages to Event Integration Architecture"
                }
            ]
        }
    }
}